{"name":"build-javascript","namedChunkGroups":{"app":{"name":"app","assets":[{"name":"webpack-runtime-ad69e82d1ec7795c9683.js","size":4948},{"name":"framework-241c3570380b02c9d5ab.js","size":210243},{"name":"b637e9a5-e80a5e684d689830fb10.js","size":90285},{"name":"app-a3bbef1da76cc97ba7d5.js","size":218327}],"filteredAssets":0,"assetsSize":523803,"filteredAuxiliaryAssets":4,"auxiliaryAssetsSize":1661117},"component---src-pages-404-js":{"name":"component---src-pages-404-js","assets":[{"name":"component---src-pages-404-js-4a7ea1f9125caa069516.js","size":567}],"filteredAssets":0,"assetsSize":567,"filteredAuxiliaryAssets":1,"auxiliaryAssetsSize":731},"component---src-pages-index-js":{"name":"component---src-pages-index-js","assets":[{"name":"styles.bf73db17b759407a7832.css","size":191558},{"name":"component---src-pages-index-js-0b832d08c85a7880556c.js","size":126715}],"filteredAssets":0,"assetsSize":318273,"filteredAuxiliaryAssets":2,"auxiliaryAssetsSize":311196}},"assetsByChunkName":{"app":["webpack-runtime-ad69e82d1ec7795c9683.js","framework-241c3570380b02c9d5ab.js","b637e9a5-e80a5e684d689830fb10.js","app-a3bbef1da76cc97ba7d5.js"],"component---src-pages-404-js":["component---src-pages-404-js-4a7ea1f9125caa069516.js"],"component---src-pages-index-js":["styles.bf73db17b759407a7832.css","component---src-pages-index-js-0b832d08c85a7880556c.js"]},"childAssetsByChunkName":{}}